<annotation>
	<folder>Persons</folder>
	<filename>image_988.jpg</filename>
	<path>D:\project\custom data\test\Persons\image_988.jpg</path>
	<source>
		<database>Unknown</database>
	</source>
	<size>
		<width>189</width>
		<height>267</height>
		<depth>3</depth>
	</size>
	<segmented>0</segmented>
	<object>
		<name>person</name>
		<pose>Unspecified</pose>
		<truncated>0</truncated>
		<difficult>0</difficult>
		<bndbox>
			<xmin>48</xmin>
			<ymin>4</ymin>
			<xmax>153</xmax>
			<ymax>145</ymax>
		</bndbox>
	</object>
</annotation>
